lib/__init__.py
test/__init__.py
test/test_lib.py
RUTlib-0.1.2.dist-info/LICENCE.md
RUTlib-0.1.2.dist-info/METADATA
RUTlib-0.1.2.dist-info/WHEEL
RUTlib-0.1.2.dist-info/top_level.txt
RUTlib-0.1.2.dist-info/RECORD
