Metadata-Version: 2.1
Name: RUTlib
Version: 0.1.2
Summary: A library to handle and validate Chilean RUT
Home-page: https://github.com/RUTlib/rutlib-py
Author: Felipe Vergara
Author-email: rutlibteam@gmail.com
License: MIT
Keywords: RUT,Chile,validation
Classifier: Development Status :: 5 - Production/Stable
Classifier: Intended Audience :: Developers
Classifier: Operating System :: Microsoft :: Windows :: Windows 10
Classifier: License :: OSI Approved :: MIT License
Classifier: Programming Language :: Python :: 3
License-File: LICENCE.md
